simpel_projects/__init__.py
simpel_projects/admin.py
simpel_projects/apps.py
simpel_projects/backends.py
simpel_projects/const.py
simpel_projects/helpers.py
simpel_projects/hooks.py
simpel_projects/managers.py
simpel_projects/mixins.py
simpel_projects/models.py
simpel_projects/settings.py
simpel_projects/signals.py
simpel_projects/urls.py
simpel_projects/version.py
simpel_projects/views.py
simpel_projects/migrations/0001_initial.py
simpel_projects/migrations/0002_alter_workorder_customer_id.py
simpel_projects/migrations/0003_auto_20220401_0100.py
simpel_projects/migrations/0004_auto_20220408_2358.py
simpel_projects/migrations/__init__.py
simpel_projects/templates/admin/simpel_projects/workorder_changelist.html
simpel_projects/templates/admin/simpel_projects/workorder_convert_form.html
simpel_projects/templatetags/__init__.py
simpel_projects/templatetags/simpelprojects_tags.py
simpel_projects/tests/__init__.py
simpel_projects/tests/factories.py
simpel_projects/tests/tests_api.py
simpel_projects/tests/tests_models.py
simpel_projects/tests/tests_views.py
simpel_projects-0.1.dist-info/LICENSE
simpel_projects-0.1.dist-info/METADATA
simpel_projects-0.1.dist-info/WHEEL
simpel_projects-0.1.dist-info/top_level.txt
simpel_projects-0.1.dist-info/RECORD
